proboundsviz/__init__.py
proboundsviz/proboundsviz.py
proboundsviz-0.1.0.dist-info/LICENSE
proboundsviz-0.1.0.dist-info/METADATA
proboundsviz-0.1.0.dist-info/WHEEL
proboundsviz-0.1.0.dist-info/RECORD
