Metadata-Version: 2.3
Name: proboundsviz
Version: 0.1.0
Summary: Visualizations of probounds.py outputs
License: MIT
Author: Uriah Finkel
Requires-Python: >=3.9,<4.0
Classifier: License :: OSI Approved :: MIT License
Classifier: Programming Language :: Python :: 3
Classifier: Programming Language :: Python :: 3.9
Classifier: Programming Language :: Python :: 3.10
Classifier: Programming Language :: Python :: 3.11
Classifier: Programming Language :: Python :: 3.12
Classifier: Programming Language :: Python :: 3.13
Requires-Dist: probounds (>=0.3.1,<0.4.0)
